Workbook

Sheet Methodology
A1: WSA Financial Statement Analysis Project
A3: Objective:
A4: Analyze WS Audiology’s financial performance from FY 2020/21 to FY 2024/25 using publicly available annual report data.
A6: Data Source:
A7: WS Audiology Annual Reports, primarily the FY 2024/25 restated 5-year key figures and financial ratios table.
A9: Currency:
A10: EUR million unless stated otherwise.
A12: Methodology:
A13: The analysis includes revenue trend analysis, profitability ratios, cash flow analysis, working capital indicators, leverage analysis, and dashboard visualization.
A15: Key Ratios Calculated:
A16: Revenue growth
A17: Gross margin
... A33: FY 2023/24 profitability ratios are affected by exceptional amortization of intangible assets.

Sheet Raw_Key_Figures
A1: WS Audiology Financial Statement Analysis
A2: Raw key financial figures | FY 2020/21–FY 2024/25 | EUR million unless stated otherwise
A4: Metric | B4: 2020/21 | C4: 2021/22 | D4: 2022/23 | E4: 2023/24 | F4: 2024/25
A5: Income Statement
A6: Revenue | B6: 2053 | C6: 2351 | D6: 2465 | E6: 2637 | F6: 2579
A7: Gross profit | B7: 1202 | C7: 1376 | D7: 1440 | E7: 1496 | F7: 1619
A8: EBITDA before special items | B8: — | C8: — | D8: 376 | E8: 440 | F8: 456
A9: Normalized EBITDA | B9: 385 | C9: 382 | D9: 408 | E9: — | F9: —
A10: Reported EBITDA | B10: 334 | C10: 302 | D10: 374 | E10: 419 | F10: 433
A11: Depreciation & amortization | B11: 271 | C11: 256 | D11: 259 | E11: 1403 | F11: 147
A12: EBIT | B12: 63 | C12: 47 | D12: 115 | E12: -984 | F12: 286
A13: Net financial items | B13: -190 | C13: -372 | D13: -156 | E13: -437 | F13: -248
A14: Profit/loss before tax | B14: -126 | C14: -325 | D14: -41 | E14: -1421 | F14: 38
A15: Profit/loss for the year | B15: -117 | C15: -311 | D15: -52 | E15: -1172 | F15: 4
A16: Balance Sheet
A17: Assets | B17: 6509 | C17: 6579 | D17: 6414 | E17: 5061 | F17: 5080
A18: Net interest-bearing debt | B18: 3504 | C18: 3746 | D18: 3610 | E18: 3308 | F18: 2807
A19: Net working capital | B19: 225 | C19: 284 | D19: 258 | E19: 319 | F19: 311
A20: Equity | B20: 1542 | C20: 1393 | D20: 1347 | E20: 616 | F20: 1174
A21: Cash Flow & Other Data
A22: Cash flow from operating activities | B22: 318 | C22: 248 | D22: 353 | E22: 293 | F22: 388
A23: Free cash flow | B23: 262 | C23: 203 | D23: 251 | E23: 205 | F23: 294
A24: Employees | B24: 11441 | C24: 11980 | D24: 12528 | E24: 12679 | F24: 12534
A25: Reported Ratios
A26: Organic growth % | B26: 22 | C26: 7 | D26: 7 | E26: 10 | F26: 0
A27: Gross profit margin % | B27: 59 | C27: 59 | D27: 58 | E27: 57 | F27: 63
A28: EBITDA margin before special items % | B28: — | C28: — | D28: 15 | E28: 17 | F28: 18
A29: Normalized EBITDA margin % | B29: 19 | C29: 16 | D29: 17 | E29: — | F29: —
A30: Reported EBITDA margin % | B30: 16 | C30: 13 | D30: 15 | E30: 16 | F30: 17
A31: EBIT margin % | B31: 3 | C31: 2 | D31: 5 | E31: -37 | F31: 11
A32: ROE % | B32: -7 | C32: -21 | D32: -4 | E32: -119 | F32: 0
A33: Equity ratio % | B33: 24 | C33: 21 | D33: 21 | E33: 12 | F33: 23
A35: Source: WSA Annual Report 2024/25, 5-year key figures and financial ratios table. Comparative figures are restated where applicable.

Sheet Ratio_Calculations
A1: WS Audiology Ratio Analysis
A2: Calculated financial ratios | FY 2020/21–FY 2024/25
A4: Ratio | B4: 2020/21 | C4: 2021/22 | D4: 2022/23 | E4: 2023/24 | F4: 2024/25
A5: Revenue growth | B5: - | C5: =Raw_Key_Figures!C6/Raw_Key_Figures!B6-1 -> 0.14515343 | D5: =Raw_Key_Figures!D6/Raw_Key_Figures!C6-1 -> 0.048490004 | E5: =Raw_Key_Figures!E6/Raw_Key_Figures!D6-1 -> 0.069776876 | F5: =Raw_Key_Figures!F6/Raw_Key_Figures!E6-1 -> -0.021994691
A6: Gross margin | B6: =Raw_Key_Figures!B7/tbl_raw_key_figures[[#This Row],[2020/21]] -> 0.58548466 | C6: =Raw_Key_Figures!C7/tbl_raw_key_figures[[#This Row],[2021/22]] -> 0.58528286 | D6: =Raw_Key_Figures!D7/tbl_raw_key_figures[[#This Row],[2022/23]] -> 0.5841785 | E6: =Raw_Key_Figures!E7/tbl_raw_key_figures[[#This Row],[2023/24]] -> 0.56731134 | F6: =Raw_Key_Figures!F7/tbl_raw_key_figures[[#This Row],[2024/25]] -> 0.6277627
A7: EBITDA before special items margin | B7: - | C7: - | D7: =Raw_Key_Figures!D8/Raw_Key_Figures!D6 -> 0.1525355 | E7: =Raw_Key_Figures!E8/Raw_Key_Figures!E6 -> 0.16685628 | F7: =Raw_Key_Figures!F8/Raw_Key_Figures!F6 -> 0.17681272
A8: Normalized EBITDA margin | B8: =Raw_Key_Figures!B9/Raw_Key_Figures!B6 -> 0.18753044 | C8: =Raw_Key_Figures!C9/Raw_Key_Figures!C6 -> 0.16248405 | D8: =Raw_Key_Figures!D9/Raw_Key_Figures!D6 -> 0.16551724 | E8: - | F8: -
A9: Reported EBITDA margin | B9: =Raw_Key_Figures!B10/Raw_Key_Figures!B6 -> 0.16268875 | C9: =Raw_Key_Figures!C10/Raw_Key_Figures!C6 -> 0.12845598 | D9: =Raw_Key_Figures!D10/Raw_Key_Figures!D6 -> 0.15172414 | E9: =Raw_Key_Figures!E10/Raw_Key_Figures!E6 -> 0.15889268 | F9: =Raw_Key_Figures!F10/Raw_Key_Figures!F6 -> 0.16789453
A10: EBIT margin | B10: =Raw_Key_Figures!B12/Raw_Key_Figures!B6 -> 0.0306868 | C10: =Raw_Key_Figures!C12/Raw_Key_Figures!C6 -> 0.019991493 | D10: =Raw_Key_Figures!D12/Raw_Key_Figures!D6 -> 0.046653144 | E10: =Raw_Key_Figures!E12/Raw_Key_Figures!E6 -> -0.37315131 | F10: =Raw_Key_Figures!F12/Raw_Key_Figures!F6 -> 0.1108957
A11: Net profit margin | B11: =Raw_Key_Figures!B15/Raw_Key_Figures!B6 -> -0.056989771 | C11: =Raw_Key_Figures!C15/Raw_Key_Figures!C6 -> -0.13228413 | D11: =Raw_Key_Figures!D15/Raw_Key_Figures!D6 -> -0.021095335 | E11: =Raw_Key_Figures!E15/Raw_Key_Figures!E6 -> -0.44444444 | F11: =Raw_Key_Figures!F15/Raw_Key_Figures!F6 -> 0.0015509888
A12: ROA | B12: =Raw_Key_Figures!B15/Raw_Key_Figures!B17 -> -0.017975111 | C12: =Raw_Key_Figures!C15/Raw_Key_Figures!C17 -> -0.047271622 | D12: =Raw_Key_Figures!D15/Raw_Key_Figures!D17 -> -0.0081072654 | E12: =Raw_Key_Figures!E15/Raw_Key_Figures!E17 -> -0.23157479 | F12: =Raw_Key_Figures!F15/Raw_Key_Figures!F17 -> 0.00078740157
A13: ROE | B13: =Raw_Key_Figures!B15/Raw_Key_Figures!B20 -> -0.075875486 | C13: =Raw_Key_Figures!C15/Raw_Key_Figures!C20 -> -0.22325915 | D13: =Raw_Key_Figures!D15/Raw_Key_Figures!D20 -> -0.038604306 | E13: =Raw_Key_Figures!E15/Raw_Key_Figures!E20 -> -1.9025974 | F13: =Raw_Key_Figures!F15/Raw_Key_Figures!F20 -> 0.003407155
A14: Net debt / Reported EBITDA | B14: =Raw_Key_Figures!B18/Raw_Key_Figures!B10 -> 10.491018 | C14: =Raw_Key_Figures!C18/Raw_Key_Figures!C10 -> 12.403974 | D14: =Raw_Key_Figures!D18/Raw_Key_Figures!D10 -> 9.6524064 | E14: =Raw_Key_Figures!E18/Raw_Key_Figures!E10 -> 7.8949881 | F14: =Raw_Key_Figures!F18/Raw_Key_Figures!F10 -> 6.482679
A15: Operating cash flow margin | B15: =Raw_Key_Figures!B22/Raw_Key_Figures!B6 -> 0.15489528 | C15: =Raw_Key_Figures!C22/Raw_Key_Figures!C6 -> 0.10548703 | D15: =Raw_Key_Figures!D22/Raw_Key_Figures!D6 -> 0.14320487 | E15: =Raw_Key_Figures!E22/Raw_Key_Figures!E6 -> 0.11111111 | F15: =Raw_Key_Figures!F22/Raw_Key_Figures!F6 -> 0.15044591
A16: FCF margin | B16: =Raw_Key_Figures!B23/Raw_Key_Figures!B6 -> 0.12761812 | C16: =Raw_Key_Figures!C23/Raw_Key_Figures!C6 -> 0.086346236 | D16: =Raw_Key_Figures!D23/Raw_Key_Figures!D6 -> 0.10182556 | E16: =Raw_Key_Figures!E23/Raw_Key_Figures!E6 -> 0.077739856 | F16: =Raw_Key_Figures!F23/Raw_Key_Figures!F6 -> 0.11399767
A17: NWC / Revenue | B17: =Raw_Key_Figures!B19/Raw_Key_Figures!B6 -> 0.10959571 | C17: =Raw_Key_Figures!C19/Raw_Key_Figures!C6 -> 0.12079966 | D17: =Raw_Key_Figures!D19/Raw_Key_Figures!D6 -> 0.10466531 | E17: =Raw_Key_Figures!E19/Raw_Key_Figures!E6 -> 0.1209708 | F17: =Raw_Key_Figures!F19/Raw_Key_Figures!F6 -> 0.12058938
A18: Equity ratio | B18: =Raw_Key_Figures!B20/Raw_Key_Figures!B17 -> 0.23690275 | C18: =Raw_Key_Figures!C20/Raw_Key_Figures!C17 -> 0.21173431 | D18: =Raw_Key_Figures!D20/Raw_Key_Figures!D17 -> 0.21000935 | E18: =Raw_Key_Figures!E20/Raw_Key_Figures!E17 -> 0.12171508 | F18: =Raw_Key_Figures!F20/Raw_Key_Figures!F17 -> 0.23110236
A21: *Ratios are calculated using year-end figures from the raw financial data sheet. ROE may differ from WSA’s reported ROE because WSA uses average equity. FY 2023/24 profitability ratios are affected by exceptional amortization of intangible assets.

Sheet Chart_Data
A1: WSA Chart Data
A2: Prepared data for Excel charts and Power BI dashboard
A4: Year | B4: Revenue | C4: Gross profit | D4: Gross margin | E4: Reported EBITDA | F4: Reported EBITDA margin | G4: Free cash flow | H4: FCF margin | I4: Net debt / Reported EBITDA
A5: 2020/21 | B5: 2053 | C5: 1202 | D5: 0.5855 | E5: 334 | F5: 0.1627 | G5: 262 | H5: 0.1276 | I5: 10.49
A6: 2021/22 | B6: 2351 | C6: 1376 | D6: 0.5853 | E6: 302 | F6: 0.1285 | G6: 203 | H6: 0.0863 | I6: 12.4
A7: 2022/23 | B7: 2465 | C7: 1440 | D7: 0.5842 | E7: 374 | F7: 0.1517 | G7: 251 | H7: 0.1018 | I7: 9.65
A8: 2023/24 | B8: 2637 | C8: 1496 | D8: 0.5673 | E8: 419 | F8: 0.1589 | G8: 205 | H8: 0.0777 | I8: 7.89
A9: 2024/25 | B9: 2579 | C9: 1619 | D9: 0.6278 | E9: 433 | F9: 0.1679 | G9: 294 | H9: 0.114 | I9: 6.48

Sheet Dashboard_Mockup
A1: WSA Financial Performance Dashboard
A2: FY 2020/21–FY 2024/25 | EUR million unless stated otherwise
